setup.py
dev_cache/__init__.py
dev_cache/tests.py
dev_cache.egg-info/PKG-INFO
dev_cache.egg-info/SOURCES.txt
dev_cache.egg-info/dependency_links.txt
dev_cache.egg-info/top_level.txt