Metadata-Version: 1.1
Name: dev-cache
Version: 0.1.4
Summary: Dev cache decorator with persistence to file
Home-page: UNKNOWN
Author: Alex Myasoedov
Author-email: msoedov@gmail.com
License: MIT
Platform: UNKNOWN
Classifier: Programming Language :: Python
Classifier: Programming Language :: Python :: 2.7
Classifier: Programming Language :: Python :: 3.3
Classifier: Programming Language :: Python :: 3.4
Classifier: Programming Language :: Python :: 3.5
Classifier: Programming Language :: Python :: 3.6
